volumio_webthing/__init__.py
volumio_webthing/app.py
volumio_webthing/volumio.py
volumio_webthing/volumio_event_receiver.py
volumio_webthing/volumio_webthing.py
volumio_webthing-0.16.1.dist-info/LICENSE
volumio_webthing-0.16.1.dist-info/METADATA
volumio_webthing-0.16.1.dist-info/WHEEL
volumio_webthing-0.16.1.dist-info/entry_points.txt
volumio_webthing-0.16.1.dist-info/top_level.txt
volumio_webthing-0.16.1.dist-info/RECORD
