Metadata-Version: 2.1
Name: volumio-webthing
Version: 0.16.1
Summary: Web connected volumio
Home-page: https://github.com/grro/volumio_webthing
Author: Gregor Roth
Author-email: gregor.roth@web.de
License: MIT
Keywords: webthings,home automation,volumio,radio,audio
Platform: UNKNOWN
Classifier: Programming Language :: Python :: 3
Classifier: License :: OSI Approved :: Apache Software License
Classifier: Operating System :: OS Independent
Classifier: Development Status :: 3 - Alpha
Requires-Dist: webthing (==0.15.0)
Requires-Dist: requests (==2.26.0)
